{
  "todos": [
    {
      "name": "veena waghunde",
      "email": "nawleveena378@gmail.com",
      "phone": "0465306245",
      "completed": false,
      "id": 1
    },
    {
      "name": "veena waghunde",
      "email": "nawleveena378@gmail.com",
      "phone": "0465306245",
      "completed": false,
      "id": 2
    },
    {
      "name": "Dnyandeo waghunde",
      "email": "dnyanu.waghunde@gmail.com",
      "phone": "0465306245",
      "completed": false,
      "id": 3
    },
    {
      "name": "veena waghunde",
      "email": "nawleveena378@gmail.com",
      "phone": "0465306245",
      "completed": false,
      "id": 4
    }
  ]
}